{
 "aggregate_function_based_on": "",
 "creation": "2025-05-29 18:25:59.998578",
 "docstatus": 0,
 "doctype": "Number Card",
 "document_type": "SVA User",
 "dynamic_filters_json": "[]",
 "filters_json": "[[\"SVA User\",\"workflow_state\",\"=\",\"Approved\",false],[\"SVA User\",\"role_profile\",\"=\",\"Volunteer\",false]]",
 "function": "Count",
 "idx": 0,
 "is_public": 1,
 "is_standard": 1,
 "label": "Approved Volunteers Registered",
 "modified": "2025-05-29 18:52:17.350459",
 "modified_by": "Administrator",
 "module": "Mykartavya",
 "name": "Approved Volunteers Registered",
 "owner": "Administrator",
 "parent_document_type": "",
 "report_function": "Sum",
 "show_percentage_stats": 0,
 "stats_time_interval": "Daily",
 "type": "Document Type"
}