{
 "app": "myKartavya ",
 "charts": [],
 "content": "[{\"type\":\"header\",\"data\":{\"text\":\"MyKartavya \"}}]",
 "creation": "2025-03-10 15:08:54.191819",
 "custom_blocks": [],
 "docstatus": 0,
 "doctype": "Workspace",
 "for_user": "",
 "hide_custom": 0,
 "icon": "users",
 "idx": 0,
 "indicator_color": "green",
 "is_hidden": 0,
 "label": "MyKartavya User",
 "link_to": "SVA User",
 "link_type": "DocType",
 "links": [],
 "modified": "2025-03-10 19:55:39.681915",
 "modified_by": "Administrator",
 "module": "Mykartavya",
 "name": "MyKartavya User",
 "number_cards": [],
 "owner": "Administrator",
 "parent_page": "",
 "public": 1,
 "quick_lists": [],
 "roles": [],
 "sequence_id": 23.0,
 "shortcuts": [],
 "title": "MyKartavya User",
 "type": "Link"
}