[
 {
  "docstatus": 0,
  "doctype": "SDG",
  "modified": "2025-03-17 10:17:05.843349",
  "name": "Affordable and Clean Energy",
  "sdg": "Affordable and Clean Energy",
  "sdg_image": "https://d3rpb3nm2k64v3.cloudfront.net/Frappe/sdg/E_SDG_PRINT-07.jpg"
 },
 {
  "docstatus": 0,
  "doctype": "SDG",
  "modified": "2025-03-17 10:19:37.742388",
  "name": "Sustainable Cities and Communities",
  "sdg": "Sustainable Cities and Communities",
  "sdg_image": "https://d3rpb3nm2k64v3.cloudfront.net/Frappe/sdg/E_SDG_PRINT-11.jpg"
 },
 {
  "docstatus": 0,
  "doctype": "SDG",
  "modified": "2025-03-17 10:26:21.425766",
  "name": "Responsible Consumption and Production",
  "sdg": "Responsible Consumption and Production",
  "sdg_image": "https://d3rpb3nm2k64v3.cloudfront.net/Frappe/sdg/E_SDG_PRINT-12.jpg"
 },
 {
  "docstatus": 0,
  "doctype": "SDG",
  "modified": "2025-03-17 10:19:12.423180",
  "name": "Reduced Inequality",
  "sdg": "Reduced Inequality",
  "sdg_image": "https://d3rpb3nm2k64v3.cloudfront.net/Frappe/sdg/E_SDG_PRINT-10.jpg"
 },
 {
  "docstatus": 0,
  "doctype": "SDG",
  "modified": "2025-03-17 10:15:42.548165",
  "name": "Quality Education",
  "sdg": "Quality Education",
  "sdg_image": "https://d3rpb3nm2k64v3.cloudfront.net/Frappe/sdg/E_SDG_PRINT-04.jpg"
 },
 {
  "docstatus": 0,
  "doctype": "SDG",
  "modified": "2025-03-17 10:35:41.736901",
  "name": "Peace Justice and Strong Institutions",
  "sdg": "Peace Justice and Strong Institutions",
  "sdg_image": "https://d3rpb3nm2k64v3.cloudfront.net/Frappe/sdg/E_SDG_PRINT-16.jpg"
 },
 {
  "docstatus": 0,
  "doctype": "SDG",
  "modified": "2025-03-17 10:28:05.515848",
  "name": "Partnerships for the Goals",
  "sdg": "Partnerships for the Goals",
  "sdg_image": "https://d3rpb3nm2k64v3.cloudfront.net/Frappe/sdg/E_SDG_PRINT-17.jpg"
 },
 {
  "docstatus": 0,
  "doctype": "SDG",
  "modified": "2025-03-17 10:14:26.964642",
  "name": "No Poverty",
  "sdg": "No Poverty",
  "sdg_image": "https://d3rpb3nm2k64v3.cloudfront.net/Frappe/sdg/E_SDG_PRINT-01.jpg"
 },
 {
  "docstatus": 0,
  "doctype": "SDG",
  "modified": "2025-03-17 10:27:41.642117",
  "name": "Life on Land",
  "sdg": "Life on Land",
  "sdg_image": "https://d3rpb3nm2k64v3.cloudfront.net/Frappe/sdg/E_SDG_PRINT-15.jpg"
 },
 {
  "docstatus": 0,
  "doctype": "SDG",
  "modified": "2025-03-17 10:27:18.503871",
  "name": "Life Below Water",
  "sdg": "Life Below Water",
  "sdg_image": "https://d3rpb3nm2k64v3.cloudfront.net/Frappe/sdg/E_SDG_PRINT-14.jpg"
 },
 {
  "docstatus": 0,
  "doctype": "SDG",
  "modified": "2025-03-17 10:15:17.410059",
  "name": "Good Health and Well-being",
  "sdg": "Good Health and Well-being",
  "sdg_image": "https://d3rpb3nm2k64v3.cloudfront.net/Frappe/sdg/E_SDG_PRINT-03.jpg"
 },
 {
  "docstatus": 0,
  "doctype": "SDG",
  "modified": "2025-03-17 10:16:04.835185",
  "name": "Gender Equality",
  "sdg": "Gender Equality",
  "sdg_image": "https://d3rpb3nm2k64v3.cloudfront.net/Frappe/sdg/E_SDG_PRINT-05.jpg"
 },
 {
  "docstatus": 0,
  "doctype": "SDG",
  "modified": "2025-03-17 10:18:05.706909",
  "name": "Decent Work and Economic Growth",
  "sdg": "Decent Work and Economic Growth",
  "sdg_image": "https://d3rpb3nm2k64v3.cloudfront.net/Frappe/sdg/E_SDG_PRINT-08.jpg"
 },
 {
  "docstatus": 0,
  "doctype": "SDG",
  "modified": "2025-03-17 10:12:43.072576",
  "name": "Zero Hunger",
  "sdg": "Zero Hunger",
  "sdg_image": "https://d3rpb3nm2k64v3.cloudfront.net/Frappe/sdg/E_SDG_PRINT-02.jpg"
 },
 {
  "docstatus": 0,
  "doctype": "SDG",
  "modified": "2025-03-17 10:18:49.551170",
  "name": "Industry Innovation and Infrastructure",
  "sdg": "Industry Innovation and Infrastructure",
  "sdg_image": "https://d3rpb3nm2k64v3.cloudfront.net/Frappe/sdg/E_SDG_PRINT-09.jpg"
 },
 {
  "docstatus": 0,
  "doctype": "SDG",
  "modified": "2025-03-17 10:16:31.519673",
  "name": "Clean Water and Sanitation",
  "sdg": "Clean Water and Sanitation",
  "sdg_image": "https://d3rpb3nm2k64v3.cloudfront.net/Frappe/sdg/E_SDG_PRINT-06.jpg"
 },
 {
  "docstatus": 0,
  "doctype": "SDG",
  "modified": "2025-03-17 10:26:48.636007",
  "name": "Climate Action",
  "sdg": "Climate Action",
  "sdg_image": "https://d3rpb3nm2k64v3.cloudfront.net/Frappe/sdg/E_SDG_PRINT-13.jpg"
 }
]